ayc/__init__.py
ayc-0.1.dist-info/METADATA
ayc-0.1.dist-info/WHEEL
ayc-0.1.dist-info/top_level.txt
ayc-0.1.dist-info/RECORD
