Metadata-Version: 2.1
Name: ayc
Version: 0.1
Summary: The funniest joke in the world
Home-page: https://github.com/aycandv/package-test
Author: Aycan Deniz Vit
Author-email: avit16@ku.edu.tr
License: MIT
Platform: UNKNOWN
